setup.py
herbiv/analysis.py
herbiv/compute.py
herbiv/get.py
herbiv/output.py
herbiv-0.1a8.dist-info/METADATA
herbiv-0.1a8.dist-info/WHEEL
herbiv-0.1a8.dist-info/licenses/LICENSE
herbiv-0.1a8.dist-info/RECORD
