Metadata-Version: 2.1
Name: herbiv
Version: 0.1a8
Summary: HerbiV(Bidirectional and Visible Database of Herb)既是一个数据库，又是一个强大的数据分析平台，集成了50多万条方剂、中药、成分、靶点数据，以及经过检验的数据挖掘模型。HerbiV is far more than a database, which is also a powerful data analysis platform that integrates more than 500,000 prescriptions, traditional Chinese medicine, ingredients and target data. Moreover, two tested data mining models are contained in HerbiV.
Project-URL: Homepage, https://github.com/MLi-lab-Bioinformatics-NJUCM/pharmastar
Project-URL: Bug Tracker, https://github.com/MLi-lab-Bioinformatics-NJUCM/pharmastar/issues
Author-email: 王皓阳 <Wesady@qq.com>
License-File: LICENSE
Classifier: Development Status :: 3 - Alpha
Classifier: Intended Audience :: Healthcare Industry
Classifier: Intended Audience :: Science/Research
Classifier: License :: OSI Approved :: MIT License
Classifier: Natural Language :: Chinese (Simplified)
Classifier: Natural Language :: English
Classifier: Operating System :: OS Independent
Classifier: Programming Language :: Python :: 3
Classifier: Topic :: Scientific/Engineering :: Bio-Informatics
Classifier: Topic :: Scientific/Engineering :: Information Analysis
Requires-Python: >=3.8
